{"contents": ["State", "Population", "Cows", "Colour", "Acre", "790101", "1736100", "#e6ab02", "Alagoas", "3321730", "919865", "#1b9e77", "Amapa", "750912", "78815", "#7570b3", "Amazonas", "3873743", "1170638", "#1b9e77", "Bahia", "15126371", "10229459", "#e6ab02", "Ceara", "8842791", "2162843", "#d95f02", "Espirito Santo", "3885049", "1791501", "#e7298a", "Goias and Distrito Federal", "9375594", "18315989", "#1b9e77", "Maranhao", "6850884", "5812164", "#7570b3", "Mato Grosso", "3224357", "20666147", "#e6ab02", "Mato Grosso do Sul", "2619657", "20634817", "#d95f02", "Minas Gerais", "20734097", "20332335", "#7570b3", "Para", "8073924", "14012698", "#e7298a", "Paraiba", "3943885", "1354457", "#7570b3", "Parana", "11081692", "9118107", "#e6ab02", "Pernambuco", "9277727", "1880432", "#e7298a", "Piaui", "3194718", "1667456", "#66a61e", "Rio de Janeiro", "16461173", "1924217", "#e6ab02", "Rio Grande do Norte", "3408510", "907185", "#66a61e", "Rio Grande do Sul", "11207274", "11334510", "#1b9e77", "Rondonia", "1748531", "8542726", "#e7298a", "Roraima", "496936", "536396", "#d95f02", "Santa Catarina", "6727148", "3126002", "#e7298a", "Sao Paulo", "44035304", "10506430", "#66a61e", "Sergipe", "2219574", "899298", "#e7298a", "Tocantins", "1496880", "6565729", "#d95f02"], "edit_mask": [{"col": 0, "row": null, "editable": false}, {"col": 1, "row": null, "editable": false}, {"col": null, "row": 0, "editable": false}, {"col": 3, "type": "color", "row": null}, {"col": 2, "min": 0, "type": "number", "row": null, "max": null}, {"col": null, "type": "text", "row": 0}, {"col": 2, "row": 0, "editable": true}], "name": "Brazil (Combined Goias and DF)", "width": 4, "height": 27}